{"users":[{"_id":"5f2ec80b-5a53-49dd-aaea-4cc60f4f5701","id":1,"full_name":"Angelina Kihn","email":"vicente.goyette@yahoo.com","phone_number":"866-668-5848","address":"118 Gorczany Trail\nSouth Madisen, NE 79529-1813","job":"School Social Worker","company":"Becker, Rippin and Waters","card_type":"MasterCard","account_number":"4556332642310798"},{"_id":"6c48bcb7-3932-4c4f-80a3-e649d96a24da","id":2,"full_name":"Ofelia Nolan","email":"gbosco@yahoo.com","phone_number":"1-844-930-4243","address":"379 Duane Street Suite 362\nBenstad, IL 17617","job":"Casting Machine Operator","company":"Bechtelar Group","card_type":"Visa","account_number":"5308855562272109"},{"_id":"577417a4-ca06-45bc-b92c-0cb4023ed2ec","id":3,"full_name":"Newell Kautzer","email":"arenner@morissette.com","phone_number":"866.451.0749","address":"4088 Zoie Manor\nLake Sanfordborough, ID 52439","job":"Computer Programmer","company":"Blanda-Koss","card_type":"MasterCard","account_number":"4539586141646455"},{"_id":"401e1258-71c3-4600-8922-66626cd8358e","id":4,"full_name":"Silas Wilkinson","email":"rahul47@hotmail.com","phone_number":"866-278-2686","address":"80882 Erik Corner\nNew Tyson, OH 65444","job":"Pest Control Worker","company":"Murazik-Williamson","card_type":"Visa Retired","account_number":"4418086418688278"},{"_id":"b35db368-9a1a-4f43-b0ff-ae8e97c48a10","id":5,"full_name":"Sonny Collins","email":"balistreri.wilma@larkin.com","phone_number":"888.235.0907","address":"9338 Arlene Summit\nShannonfurt, OR 72424","job":"Broadcast Technician","company":"Swift PLC","card_type":"MasterCard","account_number":"5181083039098773"},{"_id":"1e8ee677-0924-4db9-95e9-7df79950d245","id":6,"full_name":"Jonathon Thompson","email":"vtrantow@hotmail.com","phone_number":"855.903.5784","address":"84806 Mariam Crescent Apt. 006\nEast Modesto, CA 32741-0963","job":"Computer Operator","company":"Considine-Flatley","card_type":"Visa","account_number":"4024007181778597"},{"_id":"48819d2b-8e4b-43d2-bf7e-0d469c69fb2e","id":7,"full_name":"Delilah Marquardt","email":"brandi.durgan@gleason.net","phone_number":"(866) 972-5973","address":"4336 Kertzmann Way\nConnellyview, MA 08972-4428","job":"Bartender","company":"Pouros-Goodwin","card_type":"Discover Card","account_number":"4024007103969969"},{"_id":"2fee5efc-aa4e-43aa-a18d-c46c55f32097","id":8,"full_name":"Dr. Tessie Stoltenberg PhD","email":"jakob.hessel@hotmail.com","phone_number":"855.548.3707","address":"7122 Reinhold Views\nRollinview, ID 03434","job":"Commercial Diver","company":"Treutel, Bergnaum and Zieme","card_type":"Visa","account_number":"2672881461795565"},{"_id":"70757f46-cd55-4460-87d6-087c8bd0da7f","id":9,"full_name":"Mrs. Marisa Considine","email":"lela12@hotmail.com","phone_number":"888-446-7183","address":"408 Hintz Greens Apt. 970\nNorth Elverahaven, WV 03668-4949","job":"Tree Trimmer","company":"Parker, Brown and Cormier","card_type":"MasterCard","account_number":"4929425341028891"},{"_id":"c789684a-3c90-4e45-acd3-6d4ccae7757c","id":10,"full_name":"Lily Hamill","email":"orn.brittany@crist.com","phone_number":"1-866-265-3381","address":"9979 Medhurst Radial Apt. 839\nWest Garnett, VT 38375","job":"Hoist and Winch Operator","company":"Dibbert-Rutherford","card_type":"Visa","account_number":"5516023615027008"}],"v1.users":[{"_id":"46a246c4-8efd-4a11-8162-7948c5b2e9ae","id":1,"name":"Nash Buckridge","email":"csmitham@hotmail.com","phone":"844-212-1716","address":"48070 Gleason Place\nEast Terence, IN 21548","job":"Surgeon","company":"Gottlieb-Cummings","card":"American Express","account":"3528120458928317"},{"_id":"25fb1726-972c-491b-be7c-811f71041aef","id":2,"name":"Miss Stella Muller I","email":"antonina.kuvalis@yahoo.com","phone":"1-855-613-5060","address":"21511 Sabrina Burgs Suite 715\nSammiefurt, HI 66999","job":"Diamond Worker","company":"Rosenbaum-Jacobs","card":"Visa","account":"5367170177101307"},{"_id":"a60fe50c-fc22-4149-9f33-af908d937d0a","id":3,"name":"Ruthie Swaniawski","email":"bettie54@yahoo.com","phone":"800.892.3743","address":"59543 Pfannerstill Plains Apt. 709\nNewellport, DC 33371-7992","job":"Credit Analyst","company":"McDermott, Schowalter and Runolfsson","card":"Visa","account":"6011412129263779"},{"_id":"488fb7d6-34db-434e-98c3-c42de646c164","id":4,"name":"Jennie Hirthe","email":"tbechtelar@rogahn.net","phone":"855.880.7806","address":"4679 Schneider Key\nNorth Okeyville, MA 65580-7405","job":"Forensic Science Technician","company":"Moen Ltd","card":"Visa","account":"4024007170316086"},{"_id":"891d0227-c394-448d-b945-aee92b07ef74","id":5,"name":"Adella Kuhn","email":"sierra.kertzmann@windler.com","phone":"(844) 373-4820","address":"9457 Carmella Run Suite 018\nAbigaleport, CO 90909-1427","job":"Team Assembler","company":"Leffler LLC","card":"Visa","account":"6011475459123475"},{"_id":"22a9dbdf-d139-4708-a1bc-22755701125c","id":6,"name":"Carli Macejkovic","email":"beahan.ezra@batz.net","phone":"(888) 275-6761","address":"45359 Jerrold Trail Suite 329\nNorth Lukas, NE 12848","job":"Occupational Therapist Assistant","company":"Miller-Lebsack","card":"Visa Retired","account":"2221378559786396"},{"_id":"7dd14284-3dea-425b-bb0e-ef7d03184352","id":7,"name":"Rosalind McKenzie","email":"dbogan@buckridge.com","phone":"800-450-0347","address":"75073 Susie Junction Suite 366\nNataliashire, HI 64045-1811","job":"Metal-Refining Furnace Operator","company":"Lesch PLC","card":"Visa","account":"3589007944991247"},{"_id":"94be943e-ec4a-4c69-937a-72828c4554f3","id":8,"name":"Winnifred Lindgren Sr.","email":"brau@nikolaus.com","phone":"877.237.8401","address":"14984 Rutherford Common Apt. 648\nLake Fredy, ND 63511-4164","job":"Food Batchmaker","company":"Rath, Rohan and Adams","card":"MasterCard","account":"5567884456756411"},{"_id":"e6b79280-7697-4922-ad11-9bc1e0c0e748","id":9,"name":"Madison Smitham","email":"elva82@shields.com","phone":"855-681-6193","address":"7555 Dominic Inlet\nNorth Maribelborough, OK 68731-4160","job":"Self-Enrichment Education Teacher","company":"Treutel-Rosenbaum","card":"Visa","account":"2550661025134189"},{"_id":"8c70fe85-a787-46a8-a98e-1e909012e2b1","id":10,"name":"Mrs. Aliyah Kshlerin PhD","email":"hyatt.tressa@lemke.com","phone":"855-256-9847","address":"9296 Kutch Drive Suite 582\nCreminfort, VA 95764-1922","job":"Computer Science Teacher","company":"Pagac, Hoppe and Bednar","card":"Visa","account":"4556113715168713"}],"v0.users":[{"_id":"8db51306-1344-4a30-ba38-6a6d0c023508","id":1,"name":"Mr. Shayne Upton DDS","email":"kylee.green@gmail.com","phone":"(888) 270-3770"},{"_id":"f83ca860-a26a-493d-9e01-670cde084865","id":2,"name":"Mrs. Nannie Little PhD","email":"rubye97@yahoo.com","phone":"800.752.1315"},{"_id":"c5f5ca3a-4887-4a9d-aef3-302e2dadcea6","id":3,"name":"Dr. Ara Carroll","email":"lwilkinson@mayer.com","phone":"877-604-8572"},{"_id":"c64da5b5-4992-4026-b543-adc2c637090e","id":4,"name":"Danielle Wunsch","email":"annalise17@gmail.com","phone":"844.906.3942"},{"_id":"e21ea9fa-2ddf-4c44-b2a2-8b1c9dbb8acb","id":5,"name":"Ms. Mabel Hyatt","email":"juliet.heller@hotmail.com","phone":"1-855-725-6028"},{"_id":"740b36be-118e-4029-a064-ef0036fc8c6e","id":6,"name":"Krystel Gutmann","email":"tyra50@eichmann.biz","phone":"(844) 862-9083"},{"_id":"e270e3d1-c3b3-4d07-9036-1ca744891b9a","id":7,"name":"Chyna Farrell","email":"valentina20@yahoo.com","phone":"866.509.6568"},{"_id":"38d0d345-1a29-4026-b00d-f1a8fc730a31","id":8,"name":"Kianna Kuhn","email":"elliott02@nolan.com","phone":"1-877-804-2045"},{"_id":"4dc9756d-6587-4652-b2f3-6aba34e0bec1","id":9,"name":"Mrs. Catherine Roberts II","email":"price57@reilly.org","phone":"877-924-8229"},{"_id":"c797f325-1374-49ab-8a85-0a26eaba7855","id":10,"name":"Caesar Considine","email":"heidenreich.roxane@gmail.com","phone":"877.823.7763"}],"articles":[{"_id":"3f4e39bc-a007-429c-9b61-7f971c3f97ad","id":1,"title":"Benchmark value-added e-business","description":"Maiores ipsa possimus voluptates fugiat rerum vero. Error ut illo quia nihil accusantium qui ut. Hic dolore dolor praesentium cumque molestiae aspernatur.","views":20157,"like":4043,"dislike":7048,"date_published":"23-06-2020"},{"_id":"e6b99d3b-3dcc-4f18-9d0e-c507a8866374","id":2,"title":"Redefine real-time initiatives","description":"Et culpa animi ut quam sed nesciunt magnam. Numquam sed dolore impedit dolor.","views":95199,"like":4761,"dislike":5276,"date_published":"24-09-1996"},{"_id":"95fe4e3b-12fd-47f4-ab59-2bf04c7c5ce0","id":3,"title":"Embrace integrated paradigms","description":"Quam dolor rem et optio ut quia fugit et. Sed est excepturi facere distinctio libero sit. Recusandae aut non possimus non expedita aut occaecati ab.","views":47529,"like":6359,"dislike":3894,"date_published":"21-11-1991"},{"_id":"dc0cef90-e5ce-4a0f-954c-fb936e56a4b2","id":4,"title":"Redefine clicks-and-mortar experiences","description":"Consequatur sed eius sint voluptatum dolorem reiciendis enim. Cumque itaque numquam numquam eum ipsa sint. Vitae repellat aspernatur a dolorem molestiae. Velit provident nostrum doloremque ut.","views":78986,"like":6483,"dislike":5707,"date_published":"08-02-2019"},{"_id":"9fcb8efd-395a-41ff-8b32-4a947d1caf47","id":5,"title":"Strategize next-generation e-tailers","description":"Sit sapiente est culpa. Porro molestiae excepturi eum et. Qui dolorum fugiat sed qui sit labore nulla. Eum exercitationem rerum sit nemo ullam magnam.","views":55634,"like":4746,"dislike":9031,"date_published":"03-01-1998"},{"_id":"b1925259-8df6-4c70-b165-1162025f006e","id":6,"title":"Innovate visionary platforms","description":"Optio numquam enim sunt a voluptas nihil. Alias aut ducimus veritatis. Cum voluptas nemo ut maxime quisquam sed. Velit consequuntur et ab vitae.","views":83419,"like":2755,"dislike":3590,"date_published":"01-07-2019"},{"_id":"66bc4f97-de6e-443c-a4b7-4081b1538faf","id":7,"title":"Scale user-centric e-business","description":"Qui ullam dicta eos voluptatum vel. Vel ipsum voluptatem facilis fugiat. Nihil enim non doloremque qui dolor tenetur culpa hic.","views":55122,"like":4845,"dislike":427,"date_published":"21-10-1974"},{"_id":"ed090d57-6100-43ad-acc3-3ffb35ec8411","id":8,"title":"Cultivate cross-media convergence","description":"Error tempora nostrum est et officia eveniet perferendis nihil. Omnis et dolor tempora non minima voluptas.","views":38335,"like":4108,"dislike":1056,"date_published":"19-10-1970"},{"_id":"8a28f691-eb24-4741-8a7d-0b16d25369cf","id":9,"title":"Integrate dot-com ROI","description":"Provident corrupti beatae sint incidunt vitae neque ut. Repellat rerum laboriosam est. Quos rerum eaque et et dolorum error. In ullam explicabo numquam nihil iure itaque illo.","views":87718,"like":9512,"dislike":160,"date_published":"22-09-2018"},{"_id":"ec54c6eb-d0a6-422f-8223-80d959683fd7","id":10,"title":"Monetize open-source systems","description":"Doloribus non voluptatibus ut quos quos dignissimos quam. Dolores ipsam dolor enim vero nam officia.","views":14090,"like":166,"dislike":9002,"date_published":"17-10-2016"}],"v1.articles":[{"_id":"0786458d-371e-4231-b78f-87c4b169eb78","id":1,"title":"Enable holistic relationships","description":"Eius amet blanditiis quia nulla. Quos cupiditate necessitatibus repellendus minima facere dolores nesciunt. Velit illo et ducimus vel. Suscipit dignissimos dolorem rerum omnis.","views":68805,"like":9342,"dislike":6605,"date_published":"31-03-1988"},{"_id":"c1cbb185-acbd-4a75-bbb6-8b9d09b0cb4e","id":2,"title":"Transition B2C systems","description":"Ex cumque iste voluptatem itaque nihil a molestiae. Rem sunt in quia aut numquam aliquid quaerat hic. Reiciendis fugiat cum et nobis nihil voluptas praesentium atque.","views":40402,"like":2890,"dislike":5801,"date_published":"24-04-1989"},{"_id":"3127b9de-50f9-463d-b411-3425cc119778","id":3,"title":"Implement turn-key applications","description":"Voluptas corporis veritatis minus consectetur aut aut. Rerum et temporibus ut voluptates molestiae inventore optio.","views":55005,"like":5061,"dislike":5843,"date_published":"06-03-2000"},{"_id":"9c0a8dcc-5110-42f3-9945-304724808add","id":4,"title":"Engage granular mindshare","description":"Beatae a provident sint repellat ut quo. Dolor ex itaque reiciendis veniam. Velit excepturi molestiae repudiandae aperiam.","views":76661,"like":7593,"dislike":2088,"date_published":"02-12-1994"},{"_id":"f2223b9d-c356-4159-8f69-275465f8aa23","id":5,"title":"Strategize revolutionary metrics","description":"Natus molestiae minus doloribus sed necessitatibus. Minima voluptas quis tempore voluptatibus aperiam fuga. Mollitia et qui accusamus.","views":83579,"like":1081,"dislike":6044,"date_published":"06-08-2002"},{"_id":"9bfbb5f3-f057-46db-a2e1-162beaa479d8","id":6,"title":"Envisioneer synergistic webservices","description":"Qui velit consequatur qui eum est praesentium dicta. Dolores debitis culpa qui voluptates. Consequatur ab sint nesciunt sunt natus. Est voluptas eius rerum quisquam vel voluptatem.","views":41931,"like":2538,"dislike":3680,"date_published":"14-09-1981"},{"_id":"818831ad-e250-47af-96d6-0cc65e3a0589","id":7,"title":"Whiteboard frictionless ROI","description":"Sit eos ut quia dolor aperiam. Sunt et explicabo assumenda. Illo cum eveniet magnam eius eligendi minima accusamus. Quos iste magni voluptates.","views":29125,"like":4618,"dislike":5822,"date_published":"29-03-1975"},{"_id":"01a0cd04-2c82-4f76-a973-c93f4f73cf46","id":8,"title":"Visualize intuitive channels","description":"Quis dolorem ducimus dolore. Illum vitae aut reprehenderit facere tempora quis. Repudiandae distinctio odio nesciunt aut.","views":95383,"like":2425,"dislike":4714,"date_published":"09-12-2008"},{"_id":"712e262e-3522-49ab-97c9-cf40f18d4b15","id":9,"title":"Transform real-time channels","description":"Et minima commodi quia sunt reprehenderit expedita. Aut sint inventore temporibus animi facilis. Illo aut dolor qui eum et aliquam.","views":28408,"like":2183,"dislike":1212,"date_published":"12-10-2013"},{"_id":"54a17cc6-d5e9-4c17-a23c-d9c4fd4b64cd","id":10,"title":"Maximize impactful portals","description":"Atque nostrum inventore aliquid ut magni voluptas. Excepturi consequatur at mollitia sunt tempora. Cumque occaecati eos ipsam libero. Minima dolorum ut ut sit.","views":67348,"like":4903,"dislike":4030,"date_published":"10-07-1989"}],"v0.articles":[{"_id":"8bbaf518-2ddd-408b-bdce-ef77c05dd235","id":1,"title":"Seize leading-edge interfaces","description":"Incidunt iste dolores voluptatum maiores ratione animi eius. Et molestiae vel eligendi nostrum tempore doloremque. Magnam quis id nihil voluptatem voluptatem incidunt esse mollitia."},{"_id":"3d5ce5a5-f11b-470a-88c1-d0314a0526e5","id":2,"title":"Revolutionize extensible portals","description":"Expedita nam omnis necessitatibus quos. Soluta repellendus veritatis sint quisquam ullam earum cumque. Enim nostrum quis quae odit quas consequatur. Nisi harum rerum ipsam laudantium quod."},{"_id":"7df7dc6a-38a7-4ade-a62b-fc5710420a4c","id":3,"title":"Incentivize proactive deliverables","description":"Sit voluptatibus nesciunt cum omnis in velit nesciunt explicabo. Corporis quam explicabo expedita vel. Dolor pariatur explicabo et dolor voluptas laborum est."},{"_id":"6773abfb-a670-463b-a4b7-6278017f9ed1","id":4,"title":"Transform revolutionary e-markets","description":"Vero corrupti maxime omnis qui beatae non enim. Et non natus illo. Voluptatem excepturi odit debitis perferendis veritatis ut. Dolores ex expedita est id natus id non quam."},{"_id":"96da4268-1071-4e57-9a9c-7f99593d3f51","id":5,"title":"Expedite dynamic infomediaries","description":"Non et asperiores non et omnis harum in. Temporibus dolor non labore sapiente nihil. Et dolore iste sint nihil. Ut rerum recusandae in ducimus."},{"_id":"74d979d7-b229-4e39-ab32-803c596d762d","id":6,"title":"Scale B2C e-tailers","description":"Itaque quo vero ut tenetur iure. Cumque aut et voluptas. Earum voluptas consequatur commodi dolorum in autem. Eum harum et placeat aut aut quam. Ut modi dolore quod perferendis."},{"_id":"5afee99d-5095-4299-9bf4-a93d416c6efb","id":7,"title":"Generate cutting-edge ROI","description":"Quam odio rerum perferendis voluptas quisquam id et consequatur. Numquam cum in omnis autem reiciendis cupiditate. Est id ipsum aliquid autem quisquam non."},{"_id":"faa6a53b-1297-4791-a97b-a9246b43d80b","id":8,"title":"Envisioneer wireless niches","description":"Qui repellat eos et provident facere et. Adipisci reprehenderit distinctio ex temporibus. Maxime minima odio voluptatem facere distinctio excepturi provident. Illo iste dicta et harum."},{"_id":"568f3a37-56f6-4e0c-b331-1f07fb498641","id":9,"title":"Envisioneer B2B convergence","description":"Est autem sit qui deleniti ad. Omnis distinctio occaecati neque recusandae. Non illum itaque fugiat. Culpa molestiae et dolores quia quo velit."},{"_id":"34697c66-2c7a-4aea-80f9-adaba022e6a6","id":10,"title":"Engage dynamic e-markets","description":"Deserunt ullam deleniti et in rem atque pariatur. Voluptate quasi fuga vel. Explicabo est ipsa aut autem aut exercitationem. Repellendus quis eligendi saepe occaecati."}]}