{"users":[{"_id":"6e9fb0c1-eef6-4af1-b1fd-2b2312009c51","id":1,"full_name":"Mrs. Margaretta Braun","email":"marcelle.mclaughlin@gorczany.info","phone_number":"800-346-2061","address":"8845 Fabian Parkway\nKatelynnchester, TX 44126-5850","job":"Welder and Cutter","company":"Rippin, Quigley and Hoeger","card_type":"MasterCard","account_number":"2720174980129330"},{"_id":"626d3ffd-963a-40ee-8658-407ab1ceda93","id":2,"full_name":"Robin Hirthe","email":"shad.kautzer@casper.biz","phone_number":"855-989-8135","address":"4964 Abdul Pines Suite 023\nPort Ernestineville, NE 70456-2974","job":"Railroad Conductors","company":"Stark-Brekke","card_type":"MasterCard","account_number":"348399555147583"},{"_id":"46e04409-0c40-44d2-a3c1-342a5f6a2221","id":3,"full_name":"Holly Macejkovic","email":"bogisich.kenna@feil.com","phone_number":"800.396.8939","address":"7095 Reynolds Crossroad\nNorth Katelinstad, MS 50944-0635","job":"Biochemist or Biophysicist","company":"Cremin, Moen and Mueller","card_type":"MasterCard","account_number":"375162700503852"},{"_id":"0bd39841-0804-45c2-ae30-fe7d95e1b918","id":4,"full_name":"Rogelio Hermiston","email":"taurean97@gmail.com","phone_number":"(877) 665-4481","address":"296 Cedrick Dale\nLeonorfurt, VT 91649","job":"Substation Maintenance","company":"Olson-Kuhlman","card_type":"MasterCard","account_number":"4716341051778582"},{"_id":"71497921-2999-4368-8535-766014df618b","id":5,"full_name":"Prof. Deshawn Wehner","email":"rdietrich@gleason.net","phone_number":"888.386.8618","address":"3186 Windler Tunnel\nEast Greenton, IL 72236","job":"Manufactured Building Installer","company":"Barrows-Boyle","card_type":"Visa","account_number":"6011749655004832"},{"_id":"d9e06a75-6ef1-4cc6-a38f-d89233e055e0","id":6,"full_name":"Prof. Trace Hartmann III","email":"nstroman@hessel.com","phone_number":"855-942-7265","address":"5069 Hildegard Crossroad Suite 111\nEstellport, HI 91774","job":"Outdoor Power Equipment Mechanic","company":"DuBuque-Okuneva","card_type":"MasterCard","account_number":"4929673289504361"},{"_id":"340ea91e-33b5-4e00-a454-c86a3d798251","id":7,"full_name":"Ms. Freeda Gottlieb","email":"deangelo.stiedemann@hotmail.com","phone_number":"(877) 991-3462","address":"794 Bahringer Bypass Suite 990\nBaumbachview, DC 19458-9462","job":"Marketing VP","company":"Hagenes-McClure","card_type":"American Express","account_number":"4929493874099"},{"_id":"beb4abba-54a7-45fc-a1ae-acb976f606c7","id":8,"full_name":"Dr. Brent Terry IV","email":"sallie39@gmail.com","phone_number":"877.432.7438","address":"6783 Madaline Ports Apt. 168\nGusikowskihaven, AR 87355-3300","job":"Sound Engineering Technician","company":"O'Keefe, Grimes and Cremin","card_type":"Visa","account_number":"3528398575295279"},{"_id":"eb76e224-0dbc-41fe-824a-0b7e76e63e71","id":9,"full_name":"Odessa Macejkovic","email":"marjorie85@gmail.com","phone_number":"(888) 572-5351","address":"15105 Harvey Corner\nNathanchester, WY 86381","job":"Plating Operator","company":"Schinner, Fisher and Morissette","card_type":"MasterCard","account_number":"5339435707803341"},{"_id":"6f82ecb3-ac28-4a6f-987c-c2d760b3d66c","id":10,"full_name":"Prof. Carmel Heidenreich III","email":"nlangosh@veum.com","phone_number":"(866) 625-5699","address":"2881 Leonardo Overpass\nPort Bill, LA 48400","job":"Sailor","company":"O'Kon-Carter","card_type":"American Express","account_number":"4916257562771775"}],"v1.users":[{"_id":"cfba065b-3489-4c47-a2ae-f593ce679ae1","id":1,"name":"Elenora Mertz I","email":"madalyn.walker@durgan.com","phone":"(800) 826-1520","address":"10609 Kuhn Gardens Suite 811\nNedberg, NH 17585","job":"Computer","company":"Homenick-Satterfield","card":"American Express","account":"4485091219501793"},{"_id":"2dbe74d4-7115-4f65-918a-e0e4f086891e","id":2,"name":"Concepcion Rath","email":"schaefer.yolanda@gmail.com","phone":"866-802-5621","address":"6307 Rutherford Track\nNorth Chasity, CA 99083-0858","job":"Custom Tailor","company":"Stracke-Kozey","card":"Visa","account":"3589217799110336"},{"_id":"017b71eb-00c8-4a02-947a-baa3756d0698","id":3,"name":"Brenden Ward","email":"marcelle.johnson@gmail.com","phone":"1-800-537-5911","address":"8040 Gorczany Passage\nThompsonside, MT 04657-6707","job":"Cutting Machine Operator","company":"Rutherford and Sons","card":"Visa","account":"4929620844253471"},{"_id":"5e5d1679-1903-4e9b-8eec-8ccb39bd58b1","id":4,"name":"Mrs. Fatima Kris","email":"ztremblay@gmail.com","phone":"1-800-813-2489","address":"2649 Sherwood Stravenue Suite 814\nKiehnhaven, MO 78347","job":"Market Research Analyst","company":"Price Inc","card":"American Express","account":"2400612782388106"},{"_id":"5d6230b6-fb15-457d-9b76-9094c33d8f3c","id":5,"name":"Dr. Kamren Oberbrunner DDS","email":"achamplin@harber.com","phone":"(800) 843-5789","address":"145 Hills Lakes\nWest Deronport, HI 13688-4000","job":"Environmental Engineer","company":"Denesik-Johnston","card":"American Express","account":"5336386094835417"},{"_id":"bdd01df4-17ca-4998-85ba-cbc49b8710f5","id":6,"name":"Bryce Casper","email":"halie.mills@gaylord.org","phone":"855.475.6329","address":"750 Viola Radial Suite 963\nSouth Reba, LA 39138","job":"Data Processing Equipment Repairer","company":"Gutmann, Bednar and Towne","card":"Visa","account":"2221957466425576"},{"_id":"98e66a66-eff4-468c-a636-d82e9bfc3158","id":7,"name":"Hermina Doyle","email":"forest27@hotmail.com","phone":"888-283-0255","address":"919 Bauch Cliffs\nSouth Filomena, AK 15575-3877","job":"Court Reporter","company":"Trantow, Corkery and Bergstrom","card":"MasterCard","account":"2365921259343905"},{"_id":"925d1c40-d9bc-4a32-b093-1c31c1f25474","id":8,"name":"Frederique Schinner","email":"america.denesik@funk.net","phone":"1-844-799-6939","address":"89115 Schiller Garden\nPort Antonettaland, SC 75979-9782","job":"Administrative Services Manager","company":"Sauer, Ritchie and Labadie","card":"MasterCard","account":"3528936212826269"},{"_id":"26f47b22-2793-4272-b485-7a570e546b06","id":9,"name":"Horacio Parker","email":"philip48@marquardt.com","phone":"(855) 600-7811","address":"10225 Shanahan Port\nWest Burley, AL 96763-2192","job":"Music Composer","company":"Brakus and Sons","card":"Visa","account":"4777813704027050"},{"_id":"bad9b3bc-a5ac-4de7-b3dd-7f042292a323","id":10,"name":"Chelsea Reilly V","email":"serenity80@langosh.com","phone":"855.372.9324","address":"640 Vandervort Views Apt. 890\nNew Alainafurt, AR 36299-5229","job":"Gaming Surveillance Officer","company":"VonRueden-Bauch","card":"Discover Card","account":"4485709007860481"}],"v0.users":[{"_id":"7c322b8c-e8c8-4c81-b4d6-e6215ea1f816","id":1,"name":"Austyn Stark","email":"santiago16@bailey.biz","phone":"(844) 246-4348"},{"_id":"965c3872-02ee-4a62-9f65-e8e57a3f11df","id":2,"name":"Jonathan Walsh V","email":"lelia75@yahoo.com","phone":"(800) 762-8363"},{"_id":"a02f2526-283b-405c-9f02-8936d6419553","id":3,"name":"Erick Stehr MD","email":"janie.lehner@stoltenberg.com","phone":"877.850.9601"},{"_id":"25127868-7266-4d46-9621-50427836006f","id":4,"name":"Reba Cremin","email":"vernon69@hotmail.com","phone":"855.943.0605"},{"_id":"3d3fa7e1-9e93-4ce1-a370-3469935b0a86","id":5,"name":"Annette Klocko","email":"gutkowski.ozella@kassulke.com","phone":"866-256-2931"},{"_id":"775578d2-b33a-497b-834f-998b7fac0950","id":6,"name":"Nicolette Boehm","email":"mccullough.estella@yahoo.com","phone":"(888) 528-8515"},{"_id":"3ba1828d-8b33-40b6-a1a2-10d4880a3f62","id":7,"name":"Mr. Cristobal Hintz MD","email":"mya27@johnston.com","phone":"(888) 927-5358"},{"_id":"44e91b52-af87-4b22-9365-50e68e46e8f4","id":8,"name":"Marguerite Buckridge Sr.","email":"mmitchell@heidenreich.com","phone":"888-312-6058"},{"_id":"db26747d-3583-4208-881f-931e99f38920","id":9,"name":"Jamal Watsica","email":"ldurgan@hotmail.com","phone":"(800) 236-6308"},{"_id":"a46ece89-3b46-4e7c-ba62-12573a243598","id":10,"name":"Brandt Kemmer","email":"rlockman@boehm.com","phone":"1-866-800-5127"}],"articles":[{"_id":"0333d1f9-cafd-4656-9f40-9032a975cfaa","id":1,"title":"Incubate virtual portals","description":"Nihil quisquam enim sequi voluptatem. Molestias consequatur nobis inventore ad. Adipisci iusto sequi iure ad velit omnis doloribus.","views":49065,"like":4629,"dislike":3351,"date_published":"05-06-2020"},{"_id":"161c2fa0-6b89-4de4-b4f7-b8c7e5f52ef6","id":2,"title":"Engage value-added initiatives","description":"Harum aut praesentium aut alias est velit consequuntur vero. Est alias tempora blanditiis.","views":43356,"like":7688,"dislike":4770,"date_published":"17-03-2022"},{"_id":"0c5538bf-b7d0-4172-8ab3-a61c46d20c68","id":3,"title":"Optimize transparent e-markets","description":"Recusandae sit voluptatibus aliquam. Amet dolor non ea voluptatibus expedita ullam ut. Sed qui repellat maxime dolores voluptas ab vel. Harum tenetur non illo quasi numquam nobis.","views":54068,"like":7280,"dislike":1914,"date_published":"21-07-2007"},{"_id":"3bfbb070-89ab-4e29-8596-a258e37cdb8d","id":4,"title":"Implement frictionless relationships","description":"Aut explicabo necessitatibus officiis sed aut quod. Omnis illum et dolorum enim voluptatem tempore. Quisquam architecto ut porro ad vel eligendi. Dicta excepturi quae est et voluptatem in.","views":77070,"like":6077,"dislike":400,"date_published":"22-05-1992"},{"_id":"56790823-99b1-4ef6-90fb-305db6c6656d","id":5,"title":"Enable dynamic vortals","description":"Minus necessitatibus alias blanditiis consequatur possimus. Sed est dolor maxime. Quia et est qui enim. Perspiciatis excepturi laboriosam vero ab nesciunt pariatur corporis quos.","views":71093,"like":5587,"dislike":791,"date_published":"19-03-1978"},{"_id":"65d1b665-2745-4fa3-8902-9c091bd8efc1","id":6,"title":"Target strategic content","description":"Nihil ut aut maxime sit. Fuga dolore nam non et occaecati eos dolores qui. Et unde maiores sit iusto. Minus sit a est minima.","views":91424,"like":4306,"dislike":1228,"date_published":"19-05-2021"},{"_id":"37a62157-c4ef-4dad-8f29-bb230820fb87","id":7,"title":"Iterate 24\/7 niches","description":"Reprehenderit maxime est occaecati dolor. Aliquam commodi eveniet quisquam facilis beatae commodi non.","views":63038,"like":8798,"dislike":4366,"date_published":"31-12-1989"},{"_id":"6cb1a9d8-861b-4e86-80a2-520b0ffae591","id":8,"title":"Enhance bricks-and-clicks webservices","description":"Voluptas atque ab ut tempora magnam. Sit et quia est dolorem. Velit itaque iure id dolor. Numquam aut vel aut autem voluptatem voluptatem ut.","views":15668,"like":9343,"dislike":6407,"date_published":"09-05-1987"},{"_id":"2fe51c85-be58-47c1-9070-918575523ae4","id":9,"title":"Generate enterprise e-business","description":"Distinctio magnam aut ullam velit. Est et dolor ab praesentium nihil. Dolore sunt vel sed labore est soluta facilis et.","views":33592,"like":4555,"dislike":6017,"date_published":"05-07-1998"},{"_id":"558343bc-1b33-4d40-90dc-9ea483689add","id":10,"title":"Deliver open-source metrics","description":"Soluta quaerat veniam voluptatum optio necessitatibus eos fuga. Qui qui iure voluptates quia dolores sed quasi.","views":97808,"like":9243,"dislike":9103,"date_published":"11-10-1976"}],"v1.articles":[{"_id":"d4cdf361-6cd5-4cf1-9e55-08fdcd23aa70","id":1,"title":"Syndicate 24\/7 metrics","description":"Et tempore voluptas excepturi est laudantium aut est. Voluptatem tenetur aliquam dicta aut impedit vel. Odio quia non molestiae et perspiciatis.","views":58271,"like":1207,"dislike":6514,"date_published":"05-03-1997"},{"_id":"ec673f16-6d4f-4179-9a80-f41e30587972","id":2,"title":"Strategize efficient initiatives","description":"Aut quia quo repellat ea. Officiis non incidunt saepe reiciendis in. Beatae inventore distinctio illo nesciunt dolore ipsa velit. Et et quae sit dolorem non iusto.","views":33399,"like":6956,"dislike":9896,"date_published":"03-08-1984"},{"_id":"f4e626b1-95ff-4d45-87fb-e4ee52568248","id":3,"title":"Cultivate mission-critical ROI","description":"Quam et ea non consequuntur. In consequatur inventore voluptatem aperiam. Sit maiores blanditiis et quis temporibus.","views":13136,"like":8060,"dislike":2911,"date_published":"21-03-2004"},{"_id":"72f7a254-3194-4cd0-98b8-00c3b24f6033","id":4,"title":"Orchestrate granular ROI","description":"Aliquid esse animi corporis occaecati. Pariatur ipsam illo est ea quia voluptas. Vero dolores minus laborum dolores. Labore soluta quo laboriosam id est. Sunt qui doloremque optio assumenda.","views":78090,"like":6789,"dislike":8145,"date_published":"29-10-2009"},{"_id":"a6c99504-4817-4e10-94ad-5e61f932673b","id":5,"title":"Exploit B2C platforms","description":"Maxime neque qui aut sunt et. Numquam dicta consequatur eaque mollitia in. Magnam quam esse quia libero voluptas sit laudantium. Eligendi eveniet in est eos omnis.","views":43989,"like":9875,"dislike":3064,"date_published":"04-08-1999"},{"_id":"6df8012a-d8c4-4ea9-9fae-857d781134b2","id":6,"title":"Visualize next-generation architectures","description":"Suscipit quia quo in autem nobis aut. Error dolorem quasi aut magni dicta sit animi. Voluptas et repellat porro exercitationem. Exercitationem rerum est quo non. Sit inventore corporis omnis.","views":21595,"like":7598,"dislike":5532,"date_published":"21-04-1991"},{"_id":"7c83ce4a-cc1b-402b-b430-df24c290130a","id":7,"title":"Repurpose efficient convergence","description":"Labore est at aut nihil magnam velit quia minus. Suscipit dolores blanditiis veniam est. Dolor laudantium nisi doloribus sed. Qui sint et culpa eos et similique sequi fugit.","views":38780,"like":3772,"dislike":5421,"date_published":"11-12-2014"},{"_id":"18014134-7d95-44ee-9152-52a37394c65f","id":8,"title":"Evolve transparent networks","description":"Accusantium sed laborum quo temporibus. Laborum non iusto optio id. Et eius ut omnis et incidunt voluptates qui rem.","views":23678,"like":3844,"dislike":1541,"date_published":"29-01-1991"},{"_id":"173978e5-d4e4-417a-bd30-0e30948e00d2","id":9,"title":"Optimize 24\/365 metrics","description":"Ea ut eos aliquid corrupti consequatur placeat. Hic quam aut vel sit minima sint ut. Et distinctio repellat voluptates vel qui.","views":52873,"like":9562,"dislike":7421,"date_published":"10-10-1989"},{"_id":"bc2e6f6b-54a2-4a4b-b1dc-fad9288d184e","id":10,"title":"Repurpose intuitive e-tailers","description":"Totam minus numquam quo consequuntur dolores consequatur. Non ipsa ut deleniti repellendus quo officia. Occaecati sed eveniet magnam eos inventore et.","views":32597,"like":9126,"dislike":3478,"date_published":"18-12-1978"}],"v0.articles":[{"_id":"93b17558-80d0-413c-8b4e-44741b4d6c0c","id":1,"title":"Streamline bricks-and-clicks e-markets","description":"Eaque voluptatem quaerat in. Quae quisquam occaecati cupiditate nulla et alias ducimus. Quisquam vel autem atque fugiat. Consequatur natus expedita quo eum pariatur."},{"_id":"d15e2917-3669-4aab-80a8-8110742daf9c","id":2,"title":"Expedite rich portals","description":"Asperiores natus aut commodi rerum maiores ab. Dolore consequuntur ea doloribus. Quia excepturi at labore at nihil."},{"_id":"06b35e59-0f71-457a-911a-a2b991b73a90","id":3,"title":"Unleash dynamic e-tailers","description":"Nisi eum sunt cumque qui. Ut aspernatur exercitationem exercitationem aperiam quis vero facilis. Quia ut inventore sit omnis maiores sequi recusandae. Sed nisi vel omnis cumque quas aut facere."},{"_id":"eaa82652-ffbf-4772-9d69-56f8b7aa0dbe","id":4,"title":"Architect seamless mindshare","description":"Nihil qui et cumque sint ratione. Omnis voluptatem omnis consequuntur nisi. Soluta excepturi harum et soluta."},{"_id":"966edd78-ac57-44c1-93eb-d67b655722e9","id":5,"title":"Iterate synergistic communities","description":"In expedita nihil illo delectus in in. Consequatur nesciunt consectetur voluptatem porro et hic. Recusandae sapiente ab repellat ducimus reprehenderit exercitationem itaque sunt."},{"_id":"f947bb31-d84e-46e7-a56e-65685e72f48d","id":6,"title":"Reinvent wireless applications","description":"Necessitatibus necessitatibus rerum non natus pariatur explicabo. Et quia labore optio provident officia. Soluta expedita aut ab est. Sunt sapiente suscipit culpa maxime."},{"_id":"22dd3c08-6818-4b25-a14c-ce962d57e696","id":7,"title":"Facilitate transparent bandwidth","description":"Corrupti eligendi perspiciatis voluptates iste. Nisi in ipsam autem nostrum sit."},{"_id":"08e4d787-3978-4937-9dc8-1a1a6f7b9bb8","id":8,"title":"Optimize web-enabled communities","description":"Sapiente sapiente voluptas et quo ipsum esse. Rerum nisi ut rerum sit velit quo sequi dolor. Veniam accusantium fugit et praesentium cupiditate et."},{"_id":"be01dcdf-7808-4127-9f96-bd9107f7b33b","id":9,"title":"Streamline killer action-items","description":"Quisquam alias nihil est error tempora ea qui beatae. Iusto et qui harum iste earum cupiditate fugiat. Quam molestias eaque error aut ratione omnis. Rerum dolores temporibus cupiditate at."},{"_id":"e662df58-5606-498b-b026-4de697c130d3","id":10,"title":"Evolve dot-com portals","description":"Sunt omnis exercitationem laborum rerum est sunt. Ex numquam quia dolor magnam et. Ratione ut eos quidem exercitationem. Est dolores ut assumenda quisquam eveniet consequatur quo."}]}