{"users":[{"_id":"360c53dd-18cb-4595-a96d-6026050e23e2","id":1,"full_name":"Shaniya Herman","email":"dgraham@hotmail.com","phone_number":"866.771.7575","address":"7216 Koch Green Apt. 242\nSouth Jean, WI 67052","job":"Communication Equipment Worker","company":"Gleichner LLC","card_type":"MasterCard","account_number":"4556627018221002"},{"_id":"3d338732-982a-4381-a4bf-120244a45249","id":2,"full_name":"Ahmed Altenwerth","email":"arvid.kessler@hotmail.com","phone_number":"1-800-432-2236","address":"773 Reichel Creek Apt. 336\nLake Madelynmouth, HI 34988-0048","job":"Pile-Driver Operator","company":"Dare-Torp","card_type":"Visa","account_number":"4556404567628510"},{"_id":"e7ca1e8a-1841-44d7-b198-40be6d26e909","id":3,"full_name":"Adele Hahn II","email":"jbosco@glover.com","phone_number":"888.709.0936","address":"25358 Ferry Trail Apt. 037\nEast Eulah, MI 97505-0154","job":"Biologist","company":"Buckridge Ltd","card_type":"Visa","account_number":"5143845622731748"},{"_id":"2cbfd9aa-6c2b-4f12-b34d-7ea26f81897f","id":4,"full_name":"Kimberly Mann","email":"kbeier@yahoo.com","phone_number":"1-800-549-9425","address":"78210 Bert Forges Apt. 938\nLake Myrtieland, AK 06440-8023","job":"Claims Taker","company":"Pagac-Frami","card_type":"MasterCard","account_number":"2458577259473908"},{"_id":"a4187e5b-6ffa-473d-9d02-9f3540aefbb3","id":5,"full_name":"Dr. Hillard Thiel PhD","email":"treutel.albertha@corkery.info","phone_number":"844.612.1985","address":"548 Therese Points\nWest Charlieland, AK 28248-2334","job":"Poet OR Lyricist","company":"Haley, Lockman and Hermiston","card_type":"Visa","account_number":"2367580708251586"},{"_id":"6d1ca5b9-a990-4160-8d71-0fe2ada9da70","id":6,"full_name":"Everette Swift","email":"tate30@gislason.com","phone_number":"(877) 970-7085","address":"58615 Jessyca Fall Suite 206\nSouth Aniya, MS 67579","job":"Multi-Media Artist","company":"Schmitt-Romaguera","card_type":"Visa","account_number":"5295276684455990"},{"_id":"280da36f-1a66-4f3b-9911-df5db120f7de","id":7,"full_name":"Xzavier Fadel I","email":"alexandrine27@gmail.com","phone_number":"(855) 974-5159","address":"9722 Angelina Harbor\nLake Cyrilmouth, OK 71837","job":"Cutting Machine Operator","company":"Schimmel Group","card_type":"MasterCard","account_number":"5107739000954952"},{"_id":"212cfd8e-68d8-4198-84a8-2ad68becc609","id":8,"full_name":"Sandy Miller","email":"ritchie.audrey@upton.com","phone_number":"866.962.0197","address":"4849 Walker Fork Apt. 105\nAngelineville, NC 11252-2361","job":"Librarian","company":"Stamm-Fadel","card_type":"MasterCard","account_number":"3528803481017600"},{"_id":"8d2734b2-067a-4ce8-8826-73f8c8718548","id":9,"full_name":"Leanna Kilback","email":"dillan.weber@yahoo.com","phone_number":"844-902-4059","address":"423 Hamill Extension\nHassieland, MO 26127-8853","job":"Staff Psychologist","company":"Gutkowski-Gulgowski","card_type":"Visa","account_number":"2349690779186000"},{"_id":"76316975-30bc-4031-b8ce-7a9e52855e0d","id":10,"full_name":"Bernice Cartwright I","email":"pklein@hoppe.com","phone_number":"888-384-8517","address":"62010 Marquise Glen Apt. 818\nLake Domenico, AL 19504","job":"Surgeon","company":"Dibbert PLC","card_type":"Visa","account_number":"4929218719461681"}],"v1.users":[{"_id":"4a8084ba-e158-4a01-bcf8-b845f3ff16b3","id":1,"name":"Dr. Zakary Kerluke DVM","email":"katelin.rath@erdman.com","phone":"877-300-4157","address":"8488 Cole Path Suite 722\nLeschstad, AZ 99245","job":"Typesetting Machine Operator","company":"Frami, Lubowitz and Kessler","card":"Visa","account":"4916029578043022"},{"_id":"fa634dff-51c2-4668-87eb-3be6d20b9557","id":2,"name":"Vida Frami I","email":"jacobson.assunta@gmail.com","phone":"888.545.1944","address":"8958 Michaela Loop\nWaylonchester, NE 37475-8103","job":"Construction","company":"Tremblay Group","card":"Visa","account":"4532897747695375"},{"_id":"d73b63eb-002a-484f-900d-1d3a706fddf9","id":3,"name":"Timmy Schmeler II","email":"waters.kathryn@littel.com","phone":"844.340.8733","address":"370 Stephan Mills Suite 674\nNorth Theresiaberg, KS 51281","job":"Waitress","company":"Goodwin, Prohaska and Hagenes","card":"American Express","account":"2372148837068652"},{"_id":"d94c2c07-d143-4bb6-9a5f-5742c6bb8720","id":4,"name":"Elena Gleason","email":"rosario79@swift.biz","phone":"1-844-797-8399","address":"2822 Hardy Lights Suite 026\nChristiansenland, MD 23337","job":"MARCOM Manager","company":"Howell, Dach and Bins","card":"Visa","account":"4505419960958456"},{"_id":"37008abf-42c6-4367-accf-f01df37d0d88","id":5,"name":"Carolanne Kunde","email":"mlueilwitz@lockman.com","phone":"(800) 889-8914","address":"125 Simonis Village\nEichmannfurt, WY 57235","job":"Music Composer","company":"Cruickshank-Kulas","card":"Visa","account":"4532583384696"},{"_id":"fc368570-4a2d-45c4-aee6-f23ce850dc71","id":6,"name":"Marianne Abshire","email":"prudence18@hotmail.com","phone":"800-928-7591","address":"9981 Ullrich Glen\nBlairtown, MT 99751","job":"Industrial Engineering Technician","company":"Deckow Inc","card":"Visa Retired","account":"2680026949192767"},{"_id":"9a306816-4eaa-4168-a63a-fe3d4544a7ab","id":7,"name":"Elias Bartell","email":"torey92@gmail.com","phone":"888.543.3522","address":"150 Margarete Extension Suite 471\nSouth Natalie, VT 09767","job":"Environmental Scientist","company":"Miller, Eichmann and Eichmann","card":"Visa","account":"4351725555550895"},{"_id":"89847f3f-e960-4a19-ba2c-e970d049a8c3","id":8,"name":"Izabella Zboncak","email":"brice.swift@hoppe.biz","phone":"800.812.4379","address":"90361 Kristina Lights\nLake Linafort, CA 27916","job":"Funeral Attendant","company":"Koch-Hermann","card":"Visa","account":"2681632912848548"},{"_id":"658193ea-ff5a-4ddf-abcf-a33b435bd8c3","id":9,"name":"Dr. Rosario Sauer","email":"hlindgren@hotmail.com","phone":"(877) 841-0356","address":"32440 Lessie Dam Suite 825\nLake Gracie, MA 51162","job":"Etcher and Engraver","company":"Keebler-McKenzie","card":"MasterCard","account":"4929227146107494"},{"_id":"7f5b29e2-a505-45da-a327-46744bd2e889","id":10,"name":"Susana Auer","email":"winston.lebsack@gmail.com","phone":"866.750.2172","address":"5869 Corkery Green\nLeschmouth, LA 32439","job":"Proofreaders and Copy Marker","company":"Langworth-Durgan","card":"MasterCard","account":"2319277151237001"}],"v0.users":[{"_id":"e0797ba0-4feb-4392-a426-d7c3893b3b84","id":1,"name":"Prof. Jamaal Howe","email":"evans06@hotmail.com","phone":"855.502.0771"},{"_id":"eef9c18b-20a1-47e4-8817-35be11a67c72","id":2,"name":"Sierra Buckridge","email":"predovic.yessenia@thompson.org","phone":"844-489-7911"},{"_id":"375e2241-2895-45c0-b46b-92ecbf2e2012","id":3,"name":"Viviane Fahey","email":"renner.margarette@quitzon.com","phone":"(800) 813-7140"},{"_id":"83b07a90-f4d2-4bbd-b554-ab2a6db22ada","id":4,"name":"Sierra Tillman Sr.","email":"akshlerin@buckridge.info","phone":"844-271-4757"},{"_id":"6b84979c-9159-44a1-8cdb-f130360f930f","id":5,"name":"Amber McKenzie","email":"nicolas.zaria@price.com","phone":"888.986.4323"},{"_id":"ae2b3b18-b0c1-4031-990b-19dfea007df1","id":6,"name":"Federico Reichert","email":"jaskolski.alek@hotmail.com","phone":"(844) 505-1061"},{"_id":"1338c6b1-8eb8-4519-b59f-6f692c01da39","id":7,"name":"Dr. Denis Flatley I","email":"caitlyn15@yahoo.com","phone":"866.492.1759"},{"_id":"80dc3698-0270-4b24-98d1-4155f719d431","id":8,"name":"Estella Hettinger","email":"catherine18@yahoo.com","phone":"866-699-9440"},{"_id":"52eadf86-e00c-45f1-bb1b-da5baf8c64e9","id":9,"name":"Aniyah Mohr","email":"urban.little@hotmail.com","phone":"1-888-830-8384"},{"_id":"ed3057f9-6ec6-43ad-bfec-02e00d2437dd","id":10,"name":"Ms. Shea Schultz III","email":"arvilla.greenholt@lowe.com","phone":"(866) 387-7467"}],"articles":[{"_id":"f50d50f1-d950-4b91-a856-626500173c8e","id":1,"title":"Enable real-time e-business","description":"Omnis voluptatem unde et voluptatem. Omnis ut illum voluptas. Aliquam aut consequatur dolores. Beatae sed voluptatem quae. Ea atque ratione modi eveniet reiciendis assumenda.","views":76470,"like":8089,"dislike":1878,"date_published":"24-10-1993"},{"_id":"1a4fcacf-5af0-4e24-96ec-91ce53f04c02","id":2,"title":"Reinvent real-time niches","description":"Inventore eum alias et maiores. Et quasi non inventore tempore voluptates consequatur ea. Et eum quam quam amet.","views":80885,"like":3511,"dislike":2423,"date_published":"13-07-1973"},{"_id":"2cfb5d44-228b-489a-930a-5dd6d0ea0daa","id":3,"title":"Grow 24\/365 users","description":"Et dolores rem est magni voluptas. Accusamus officia dignissimos reiciendis pariatur tempora ea. Tempore esse et officia et omnis.","views":98810,"like":8629,"dislike":3621,"date_published":"15-03-2004"},{"_id":"5a1dea0a-7ac5-420e-87bd-24bdd04d0a21","id":4,"title":"Disintermediate dot-com solutions","description":"Ut fugiat sequi eos maxime. Maiores impedit maxime perferendis. Illum quia impedit ratione.","views":14149,"like":7106,"dislike":2649,"date_published":"29-01-2016"},{"_id":"a5cb779a-abe9-491e-a9e9-7dd8087cb7c1","id":5,"title":"Transform vertical content","description":"Nihil consequatur pariatur sed. Sunt eos dolor excepturi maxime. Aliquam aut aut aliquam et. Quia qui deserunt necessitatibus in in accusamus.","views":62614,"like":6689,"dislike":4295,"date_published":"28-11-2014"},{"_id":"8c8c59cb-9733-4c2d-a148-07f255d3f12e","id":6,"title":"Grow frictionless synergies","description":"Beatae eaque aut blanditiis qui delectus sed itaque. Non iste dolorem quo aut deleniti repudiandae.","views":31570,"like":9994,"dislike":5368,"date_published":"16-01-1987"},{"_id":"b322d425-ceed-4767-93c8-dd8a51a8aeba","id":7,"title":"Iterate front-end deliverables","description":"Esse est blanditiis aliquid aut. Qui eos eligendi voluptatem neque consectetur est. Nam quia rem asperiores explicabo nulla.","views":76422,"like":8194,"dislike":3087,"date_published":"10-12-1990"},{"_id":"5ea41f58-7147-47d3-a4ab-b89530235f1a","id":8,"title":"Innovate revolutionary bandwidth","description":"Deleniti nihil ea recusandae eius quaerat qui accusantium. Et incidunt enim molestiae vitae. Ab sit quia doloremque velit quis explicabo illo. Et rerum et voluptatem porro dicta nihil voluptatem.","views":40203,"like":1229,"dislike":2871,"date_published":"30-03-1972"},{"_id":"cc2a93b0-4265-4c36-91e1-07e21d818e56","id":9,"title":"Transition virtual ROI","description":"Voluptas qui doloribus illo nostrum ut. Et ut minus dolorem est et veniam minus. Incidunt perspiciatis exercitationem facere. Sit odio id perferendis perspiciatis.","views":99593,"like":5476,"dislike":5808,"date_published":"12-02-1978"},{"_id":"b89719c3-3aac-4c4d-8735-ffda9ff31266","id":10,"title":"Reinvent web-enabled networks","description":"Laboriosam cumque nihil ut omnis iste ut totam sint. Soluta ut quidem rerum dolores est harum. Qui nemo id quasi sint dolorem quas.","views":84086,"like":3257,"dislike":735,"date_published":"26-04-2022"}],"v1.articles":[{"_id":"c2e50c25-21c1-45dc-aa60-9a33d4447521","id":1,"title":"Synergize dot-com experiences","description":"Nihil asperiores libero aut ullam nihil ab neque. Quo sit voluptate assumenda reiciendis expedita quae. Dicta qui sapiente et deserunt.","views":14293,"like":9305,"dislike":5353,"date_published":"13-09-1979"},{"_id":"9237a507-bfac-4d05-b1ab-14d721031255","id":2,"title":"Iterate transparent supply-chains","description":"Id et omnis fuga neque quae incidunt illo et. Magni vitae ut animi quidem nobis deserunt labore. Soluta accusantium temporibus nihil exercitationem qui nulla iusto.","views":56271,"like":7828,"dislike":8037,"date_published":"08-06-2004"},{"_id":"42150189-8004-4d0c-a645-c4e448bfc626","id":3,"title":"Morph sexy methodologies","description":"Ducimus quia occaecati deserunt ut. Ea fugit asperiores officia sunt. Eaque doloribus sit temporibus quibusdam. Ut et molestiae fugit et excepturi deserunt velit non.","views":64697,"like":4490,"dislike":112,"date_published":"13-10-1992"},{"_id":"3a5141ab-63dd-4886-afe8-343b2793078b","id":4,"title":"Syndicate interactive bandwidth","description":"Ut qui facere sunt. Ad eveniet voluptas distinctio est magni est eligendi unde. Rem eum voluptatem at non sit sint corrupti. Animi ab harum est.","views":32770,"like":6423,"dislike":3438,"date_published":"18-03-2003"},{"_id":"6b555b1d-c59f-44c3-be83-b5ce278ea60d","id":5,"title":"Utilize cross-platform e-business","description":"Repellendus dolorum similique autem qui nobis pariatur vel. Suscipit odio animi accusantium omnis ut laborum. Ex laboriosam vero expedita possimus.","views":92127,"like":3865,"dislike":7933,"date_published":"14-02-2006"},{"_id":"28176fb8-da2d-4b35-a9a6-1d15ff500266","id":6,"title":"Utilize world-class synergies","description":"Labore nam aut omnis minima eos sed. Maiores recusandae perferendis ipsam repellat sed.","views":94725,"like":479,"dislike":6594,"date_published":"19-05-2014"},{"_id":"f0631c42-83ce-421b-b2a5-a4a0c5121768","id":7,"title":"Deliver end-to-end partnerships","description":"Laudantium ipsa autem debitis quia explicabo vel voluptatem. Dolorum debitis neque quisquam eos corporis sint maiores. Veniam dolores sit iste mollitia magnam aliquid nostrum.","views":84002,"like":4113,"dislike":7187,"date_published":"07-05-1999"},{"_id":"0d3efe7a-ebfd-4dfe-8a68-91f5cb11bf04","id":8,"title":"Synthesize customized metrics","description":"Iure aliquam nulla repudiandae qui modi quia porro. Est quaerat tempora maxime esse id corporis molestiae id. Ut sequi beatae aliquam eos. Illum autem quibusdam quia doloribus ut ut quis.","views":43511,"like":6058,"dislike":8566,"date_published":"22-12-2003"},{"_id":"6fd6ba49-4ea6-4871-a6ab-684721992562","id":9,"title":"Cultivate intuitive portals","description":"Aut quia neque reprehenderit iure reiciendis magni. Illo ad quo quis quo quidem. Dolor debitis magni dolores dolores aut enim cum. Ipsum fugiat reiciendis odit.","views":85938,"like":7251,"dislike":6229,"date_published":"15-03-2020"},{"_id":"904b013d-d678-43c1-98ed-ec89d06b9ae0","id":10,"title":"Drive dot-com supply-chains","description":"Architecto beatae recusandae eum at. Atque repudiandae quia voluptatem modi adipisci quia. Qui accusamus sint aut consequatur. Dolores consectetur atque possimus.","views":47623,"like":3538,"dislike":1953,"date_published":"20-05-1999"}],"v0.articles":[{"_id":"f6c24240-586a-457a-819b-04e07b5d57c2","id":1,"title":"Envisioneer end-to-end initiatives","description":"Tempore voluptates tempore recusandae accusamus molestiae. Aut reiciendis necessitatibus maiores fuga et esse animi. Perferendis qui velit sint qui. Officiis occaecati incidunt temporibus autem."},{"_id":"047130ca-bffe-47d4-aaa5-db486aa43f61","id":2,"title":"Strategize bleeding-edge e-tailers","description":"Voluptas non eligendi sed similique quos quo autem. Ullam unde maiores ducimus assumenda aut aspernatur. Facere perferendis sapiente saepe tenetur aut."},{"_id":"30e3f7da-1223-4eb9-a810-1eb392be2e2c","id":3,"title":"Seize strategic partnerships","description":"Culpa odit et rerum veniam omnis nihil debitis eos. Quo at quo eum ab perferendis."},{"_id":"93a19d34-a605-4055-8695-ff151a0a53be","id":4,"title":"Synthesize holistic supply-chains","description":"Quasi unde exercitationem magnam non eligendi itaque beatae. Aut fuga eum ullam illo adipisci. Iusto nulla ab autem modi est ducimus. Dolorum quaerat dolorem incidunt consequatur veniam."},{"_id":"7f22ad03-b866-4f7e-84ea-20f5905ce83d","id":5,"title":"Productize web-enabled infrastructures","description":"Dolorum quia et deserunt occaecati accusamus ipsa aperiam. Repellendus excepturi sapiente sunt esse ut id ut. Pariatur consequatur est dignissimos et laudantium."},{"_id":"7e24937a-efb4-4083-ad24-193f6c56336a","id":6,"title":"Transition value-added action-items","description":"Sapiente aut omnis qui incidunt esse eum ducimus. Odit explicabo quos aut et. Expedita eveniet molestiae rerum enim voluptatem sit aliquam. Sed velit voluptatem est ea vitae ut."},{"_id":"9db03afe-9b50-4bfc-a04e-9b00dd9c0f73","id":7,"title":"Harness distributed e-commerce","description":"Et provident omnis deserunt voluptatem qui. Neque laudantium corporis rem in corporis. Et eum omnis quis voluptas. Molestias saepe veritatis quasi necessitatibus."},{"_id":"b2e84d6c-7dd9-41ef-9596-9b371d931f03","id":8,"title":"Disintermediate holistic partnerships","description":"Ut aut eveniet impedit asperiores saepe voluptatibus. Totam quibusdam vel tempore expedita atque. Corrupti labore impedit sit vel vel error."},{"_id":"8f69c550-8d67-431f-8d8d-442ad31ae535","id":9,"title":"Maximize best-of-breed markets","description":"Laborum saepe eaque sed sit. Amet explicabo aut temporibus ut quis culpa hic. Ut ipsam laborum eaque ea. Tenetur quod eaque alias quod dolor quo."},{"_id":"6b2a8077-6a66-47e9-8d44-85efcf78855a","id":10,"title":"Orchestrate mission-critical convergence","description":"Aspernatur molestiae ea reiciendis optio quibusdam. Impedit odit dignissimos ut et. Dolorem quisquam est voluptatem quos aperiam quia natus dolores. Ut magni est id deleniti et libero neque."}]}