{"users":[{"_id":"d34e3971-d52f-4a16-a354-074761fb7812","id":1,"full_name":"Katlyn Swaniawski","email":"helga48@hotmail.com","phone_number":"800.249.0520","address":"1402 Clinton Light Apt. 501\nWest Alexiefort, VA 81605-2712","job":"Insurance Appraiser","company":"Bogisich-Schultz","card_type":"MasterCard","account_number":"2459812221880842"},{"_id":"70d41c38-2adf-4884-b1b0-e3776635124b","id":2,"full_name":"Mr. Cleo Medhurst DVM","email":"janick03@kessler.info","phone_number":"(866) 446-6567","address":"3097 Lois Locks\nNew Alba, MS 74455-6995","job":"Bindery Worker","company":"Sauer Group","card_type":"Visa","account_number":"4556408527341817"},{"_id":"e56a43df-7723-4b50-89cb-44e1f52aff99","id":3,"full_name":"Lyric Lesch","email":"chaz11@rice.com","phone_number":"888-754-3003","address":"5643 Wehner Creek\nLuisaborough, UT 72654-3275","job":"Counselor","company":"Lesch-Kuphal","card_type":"Visa Retired","account_number":"2221920936551272"},{"_id":"ae15b132-706a-4126-bde7-e2590a623fd6","id":4,"full_name":"Dr. Bailey Klein","email":"leonora21@mccullough.com","phone_number":"844-884-4527","address":"8190 Daniel Canyon\nLeonieshire, ND 00361","job":"Engraver","company":"Glover, Schowalter and Gislason","card_type":"Visa Retired","account_number":"5321647555554988"},{"_id":"c41aa8a2-2667-4c8e-b6be-43646ce4b593","id":5,"full_name":"Stevie Tremblay","email":"rwiegand@gmail.com","phone_number":"888-319-3904","address":"93351 Deckow Viaduct\nWehnerbury, UT 62785-4683","job":"Sheet Metal Worker","company":"Volkman Ltd","card_type":"Visa Retired","account_number":"4024007179794119"},{"_id":"80aade4f-65f4-464f-8330-fccc75425097","id":6,"full_name":"Ms. Stella Macejkovic III","email":"csipes@jacobi.com","phone_number":"1-877-448-2869","address":"476 Kuvalis Meadows\nPort Coraliefurt, AZ 48789","job":"Precision Devices Inspector","company":"Heller PLC","card_type":"Visa","account_number":"4556524934536771"},{"_id":"c40832f2-ad8f-4ea8-9c70-657f294b77cf","id":7,"full_name":"Mr. Walter Jast IV","email":"predovic.shayne@hotmail.com","phone_number":"1-866-514-4363","address":"956 Wyatt Fields Apt. 398\nLebsacktown, PA 58990-5208","job":"Artist","company":"Welch, Brekke and Simonis","card_type":"Visa","account_number":"4929550462112545"},{"_id":"7e6866d8-c92d-485d-b79c-69843260d2ab","id":8,"full_name":"Ms. Lindsay Windler","email":"hayes.maeve@gmail.com","phone_number":"855-425-2889","address":"91073 Jaida Mills\nGottliebville, NY 73137-8403","job":"Budget Analyst","company":"Ortiz, O'Reilly and Klein","card_type":"MasterCard","account_number":"2692786024130760"},{"_id":"ed77ed80-107e-4f72-a760-e844a1c73192","id":9,"full_name":"Elyssa Lesch","email":"christ31@mccullough.com","phone_number":"1-866-251-0446","address":"76401 Swift Brook Suite 092\nLake Alvah, MI 81474","job":"Bookkeeper","company":"Schimmel LLC","card_type":"MasterCard","account_number":"5349473845874401"},{"_id":"b086cbc3-44dc-47a1-9c8a-936d8d885a43","id":10,"full_name":"Dr. Kristopher Brown","email":"adoyle@gmail.com","phone_number":"888.841.6052","address":"92594 Clinton Highway\nSouth Maximillia, TN 44271-4311","job":"Board Of Directors","company":"Gutkowski-Hane","card_type":"MasterCard","account_number":"6011596799475737"}],"articles":[{"_id":"f1d31cd2-4a1f-49fc-bdc9-9210eb0aca7e","id":1,"title":"Synthesize proactive platforms","description":"Quia natus possimus repellendus fuga. Ut et quasi id similique fugiat illo eveniet. Rerum error ex rem et dicta delectus. Dolorum aut rerum veritatis rerum voluptas exercitationem.","views":62171,"like":5368,"dislike":3675,"date_published":"02-01-2008"},{"_id":"2b592999-7fd4-40d0-a913-19641281ece9","id":2,"title":"Optimize cross-media systems","description":"Sed itaque non perspiciatis nihil. Sunt sed dicta dolores repudiandae dicta eos. Hic iusto impedit minima hic tempora eligendi est. Velit iusto magnam saepe illum minus sit voluptas.","views":31599,"like":3055,"dislike":321,"date_published":"20-01-2011"},{"_id":"b26bce63-8c7a-4219-99bb-decfac31bd62","id":3,"title":"Grow wireless infrastructures","description":"Nesciunt assumenda inventore voluptatibus. Dicta nobis odit iste enim voluptatem possimus est saepe. Molestiae perspiciatis ut veniam recusandae at.","views":31977,"like":8335,"dislike":186,"date_published":"30-06-1978"},{"_id":"9d92058b-35f5-4fe2-a7f9-dfec1639f094","id":4,"title":"Scale compelling bandwidth","description":"Accusamus sint assumenda aut maiores. Cumque aut autem sint ipsum. In enim autem corporis perspiciatis dolor quis rerum quia.","views":20249,"like":9588,"dislike":7711,"date_published":"25-04-2008"},{"_id":"71e3bdce-4658-4c7a-b20a-d849b2c152cc","id":5,"title":"Innovate mission-critical e-markets","description":"Quis odio nihil explicabo laboriosam quod dignissimos. Incidunt ipsa et ex quos enim ut occaecati. Libero aut consectetur ut et. Atque ut libero sit tenetur accusamus nihil rerum.","views":60158,"like":5097,"dislike":9740,"date_published":"02-11-2017"},{"_id":"2f3ad328-3715-421e-8c10-628bb866a237","id":6,"title":"Expedite bleeding-edge web-readiness","description":"Similique animi veritatis ea voluptate repellendus. Et libero ipsa rerum ullam dicta nobis illum. Rerum iste enim similique adipisci.","views":95079,"like":1239,"dislike":5030,"date_published":"26-12-1983"},{"_id":"6390f434-e062-45b4-95cf-22f61665d3b2","id":7,"title":"Maximize 24\/7 methodologies","description":"Qui natus libero asperiores similique illum maxime quidem. Voluptates rerum nisi occaecati. Et ullam deserunt sunt.","views":36408,"like":2367,"dislike":4778,"date_published":"31-07-2016"},{"_id":"62292fa4-48d1-4bee-84fd-80e98892d762","id":8,"title":"Streamline clicks-and-mortar communities","description":"Quis neque rerum amet quos. Earum veniam voluptates autem. Eos officiis vitae alias et consequatur.","views":67288,"like":8694,"dislike":2993,"date_published":"01-01-2013"},{"_id":"bfb2d6bf-d48f-4fd9-9efb-0bb2bdcc89be","id":9,"title":"Facilitate 24\/365 portals","description":"Accusamus asperiores dolore aut aut assumenda corrupti. Commodi ea ab tenetur cupiditate quod omnis.","views":84126,"like":367,"dislike":6476,"date_published":"03-05-1995"},{"_id":"1a676d9b-f45c-4b67-b597-8f262a44a2f2","id":10,"title":"Iterate wireless e-services","description":"Ut ratione ex et voluptatem. Velit velit quae dolor adipisci. Enim cupiditate molestiae recusandae facilis voluptatem placeat.","views":39234,"like":441,"dislike":9132,"date_published":"03-05-2001"}]}