{"users":[{"_id":"2a95151a-6e64-434c-a41f-e8218b01d046","id":1,"full_name":"Juliana Hill","email":"juana.white@jacobi.org","phone_number":"(844) 492-3920","address":"6561 Dock Crossing Apt. 714\nSouth Veronica, PA 75731","job":"Veterinary Technician","company":"Pacocha LLC","card_type":"MasterCard","account_number":"2603215454266876"},{"_id":"fc144f1d-0854-4e33-8b30-181630bab0f1","id":2,"full_name":"Camryn Legros","email":"sheldon34@yahoo.com","phone_number":"1-877-927-7851","address":"6041 Logan Trafficway\nNorth Lorenmouth, IA 80506","job":"Occupational Therapist","company":"Walsh, McCullough and Prohaska","card_type":"Visa","account_number":"2221686921751462"},{"_id":"49ce44d8-2f18-444f-ba2c-e1ed150aa21f","id":3,"full_name":"Martine Schiller","email":"corkery.dayana@gmail.com","phone_number":"866-787-9178","address":"8409 Luettgen Ridge Suite 984\nSouth Cade, VA 91286-4199","job":"Web Developer","company":"Murazik and Sons","card_type":"MasterCard","account_number":"5550490865859199"},{"_id":"94dc9963-3a3b-4e1d-ad24-687ffac00e32","id":4,"full_name":"Nelda Hegmann IV","email":"wrath@schuppe.com","phone_number":"(800) 932-3075","address":"61017 Shanahan Cape Suite 256\nMorrisbury, AZ 05345","job":"Equal Opportunity Representative","company":"Rowe and Sons","card_type":"Visa","account_number":"6011021055518666"},{"_id":"c9b79503-4dc4-4694-af1e-735bcd2abf17","id":5,"full_name":"Jamal Veum","email":"conor21@gmail.com","phone_number":"866.622.4777","address":"29337 Bechtelar Street Apt. 640\nNew Hillary, LA 26647","job":"Internist","company":"Jones LLC","card_type":"Visa","account_number":"5102964832930534"},{"_id":"229d6d07-324b-451f-953e-5ea11ec03e8f","id":6,"full_name":"Prof. Desmond Tillman","email":"kuhlman.paige@yahoo.com","phone_number":"(877) 817-0935","address":"159 Kub Bridge\nEast Zoe, PA 11532-2415","job":"Host and Hostess","company":"Jakubowski, Klein and Keebler","card_type":"American Express","account_number":"6011891712058813"},{"_id":"25bb3507-8f39-4931-8da6-fae10396f9f8","id":7,"full_name":"Alayna Schuster","email":"gutmann.abigail@zemlak.info","phone_number":"1-877-838-7361","address":"422 Aletha Inlet Apt. 568\nNew Jacynthetown, VT 80849-6708","job":"Forming Machine Operator","company":"Runolfsdottir PLC","card_type":"American Express","account_number":"4539020939012357"},{"_id":"c1661d9c-1b04-4cf4-9ecd-d2f87d1fc7cb","id":8,"full_name":"Marilyne Ziemann","email":"laurie13@gmail.com","phone_number":"1-844-747-1835","address":"161 Dennis Street Apt. 888\nNew Orland, CT 94760-3592","job":"Advertising Sales Agent","company":"Ullrich-Gleichner","card_type":"Visa","account_number":"4916870073110869"},{"_id":"ff04f804-adde-472e-905f-ea29e4cc9f74","id":9,"full_name":"Miss Daniella Hegmann PhD","email":"george.dietrich@hotmail.com","phone_number":"877.261.6272","address":"8387 Schamberger Viaduct Suite 231\nPort Jarretshire, NJ 83870","job":"Septic Tank Servicer","company":"Donnelly-Leuschke","card_type":"MasterCard","account_number":"4916440059332034"},{"_id":"98aa42e8-fc41-46a0-b1a2-99f02e97db96","id":10,"full_name":"Jeffery Ratke","email":"caroline.ondricka@hotmail.com","phone_number":"(855) 697-7776","address":"547 Gerlach Springs\nAglaeview, NE 15142-5966","job":"Singer","company":"Halvorson, Bechtelar and Halvorson","card_type":"Visa","account_number":"5182405720061233"}],"articles":[{"_id":"2701d208-baa5-4ee0-aef4-cbc7da803ee3","id":1,"title":"Maximize wireless functionalities","description":"Quia autem deserunt tempore perferendis velit. Dolor sunt rerum quos odio hic fugiat consequatur sit. Dolores adipisci vel possimus ab animi. Eius qui eum mollitia enim.","views":83304,"like":2187,"dislike":3700,"date_published":"15-01-1996"},{"_id":"1abc0654-24e8-4cc4-822f-b9cc532932de","id":2,"title":"Benchmark distributed eyeballs","description":"Eum ducimus et nihil ipsam. Maxime non repudiandae qui. Non voluptatem itaque dolores sunt ipsam natus. Enim voluptas soluta quasi in ut sit laborum et.","views":73648,"like":1520,"dislike":6381,"date_published":"22-03-1994"},{"_id":"bfa16902-e162-462a-ba45-9dd3dcec97e9","id":3,"title":"Integrate revolutionary synergies","description":"Repellendus officiis dolor ullam optio. Vel nostrum velit reiciendis quis assumenda sint. Cumque quis et nostrum cupiditate eaque. Dolorem et eius nemo et et dolores corrupti.","views":58647,"like":5707,"dislike":7083,"date_published":"05-05-1970"},{"_id":"d64baa0b-340f-40c6-aa5e-bce34eb35a37","id":4,"title":"Synergize visionary e-business","description":"Dolore velit labore explicabo repellat labore aut est. Voluptas aut iusto odio explicabo. Et dolor vero tempore omnis aut.","views":92115,"like":3224,"dislike":7565,"date_published":"07-04-2017"},{"_id":"d145b64d-b9ca-4d63-a8f2-83a14385e958","id":5,"title":"Drive B2B functionalities","description":"Aut consequatur asperiores enim quidem beatae nihil neque. Aliquam eius id et culpa eum officiis sequi amet. Rem soluta sed facere itaque vel. Magnam illum animi vel.","views":70665,"like":3038,"dislike":9598,"date_published":"30-01-1975"},{"_id":"f2bdd484-f70b-491e-87cb-e5adaefd942f","id":6,"title":"Evolve wireless initiatives","description":"Eligendi praesentium illum porro et sint nesciunt amet. Nesciunt illo quia corrupti voluptatem dolores sint suscipit. Sit ab commodi reprehenderit id vel odio deleniti aut.","views":33546,"like":8233,"dislike":5405,"date_published":"08-02-2009"},{"_id":"c6d753f9-f2cf-491e-be0f-1439dd1fd009","id":7,"title":"Leverage enterprise content","description":"Dolor nisi dolorem debitis molestiae minima rerum eum. Odio voluptas rerum quae illo culpa aliquid qui.","views":81484,"like":3787,"dislike":4415,"date_published":"18-10-2022"},{"_id":"67b62258-d99e-4d21-a9a9-1efc20837d92","id":8,"title":"Monetize impactful methodologies","description":"Possimus cupiditate delectus et voluptatem exercitationem veniam. Ad recusandae aut architecto voluptates.","views":55487,"like":7696,"dislike":6678,"date_published":"16-04-1999"},{"_id":"398998f5-6955-456d-b731-087dba6edcda","id":9,"title":"Reintermediate robust eyeballs","description":"Rerum in rem aliquid excepturi debitis et. Vitae consequatur quis voluptate magni voluptatibus. Minus ipsum ab eos magnam iure suscipit.","views":59133,"like":3994,"dislike":5310,"date_published":"05-05-1970"},{"_id":"0595d46e-fbe7-4b12-be0d-2990e38dd816","id":10,"title":"Cultivate seamless e-business","description":"Repellat fugiat corrupti blanditiis sit corporis sit accusantium illum. Sit aut molestias omnis esse error nobis aut. Assumenda et fuga et sit nam nam.","views":58067,"like":2896,"dislike":6862,"date_published":"10-10-1986"}]}