{"users":[{"_id":"8b98a0d8-d27b-4c6d-80fe-ca9791da87dc","id":1,"full_name":"Lois Rowe","email":"lkerluke@yahoo.com","phone_number":"866.868.8915","address":"36909 Hagenes Pike Apt. 400\nOndrickachester, NM 35935-0565","job":"Fashion Model","company":"Rohan, Mraz and Nader","card_type":"Visa","account_number":"4539818332312237"},{"_id":"ada6d509-c300-44e1-9851-4ed155a3dcbb","id":2,"full_name":"Frederique Miller","email":"ismith@lakin.biz","phone_number":"1-844-884-7867","address":"46563 Luisa Manors Suite 546\nWest Sharonstad, WY 17430-6371","job":"Machine Feeder","company":"Christiansen-Kiehn","card_type":"MasterCard","account_number":"4312838883426817"},{"_id":"baa7e7fb-2a9d-4806-bd1a-1a3b20600a6e","id":3,"full_name":"Manuela Gorczany III","email":"rdicki@kuhic.org","phone_number":"(888) 937-2470","address":"633 Kariane Mall\nRolfsonfurt, WV 87273","job":"Pipefitter","company":"Abbott and Sons","card_type":"Visa","account_number":"5349816708466493"},{"_id":"7703cb38-6293-4677-9940-9fdf12aea765","id":4,"full_name":"Alden Volkman","email":"barrows.nya@price.info","phone_number":"1-844-675-8105","address":"7285 Eli Heights\nCorneliusville, IA 62788-3945","job":"Aircraft Launch Specialist","company":"Jacobson-Mayert","card_type":"Discover Card","account_number":"6011006645739641"},{"_id":"48427adf-eeb9-475e-97b0-70bafc032edd","id":5,"full_name":"Charlene Rosenbaum","email":"kohler.janessa@yahoo.com","phone_number":"877.938.3942","address":"24462 Nathaniel Ways\nBoscohaven, TX 02600-1738","job":"Tour Guide","company":"Sawayn, Breitenberg and Murphy","card_type":"MasterCard","account_number":"5568302089263209"},{"_id":"ea2d826a-fe77-4754-a55e-70f6301a547a","id":6,"full_name":"Cullen Mann","email":"ophelia.white@yahoo.com","phone_number":"866.372.5574","address":"24182 Yadira Parkways\nBethville, AZ 01845","job":"Fabric Pressers","company":"Bauch-Kuvalis","card_type":"MasterCard","account_number":"340018399793216"},{"_id":"9f3a3715-2a3d-48d8-b14b-ccad6e24ec48","id":7,"full_name":"Aniyah Larson Sr.","email":"nyah38@hotmail.com","phone_number":"(888) 385-7489","address":"369 Hoeger Trail Apt. 216\nWest Grayce, AR 19940","job":"Agricultural Equipment Operator","company":"Walker-Gorczany","card_type":"MasterCard","account_number":"4539118264138092"},{"_id":"3df31ce6-e59d-40c3-be76-27c24dfe9da4","id":8,"full_name":"Helen Block","email":"ujohnson@rutherford.com","phone_number":"844-786-0326","address":"460 Sylvan Falls Suite 101\nNew Moshe, FL 88984","job":"Law Enforcement Teacher","company":"Wisoky-Smith","card_type":"Visa","account_number":"4556399259375281"},{"_id":"c81711c8-f48d-4a71-829b-98b309e1d5d9","id":9,"full_name":"Mrs. Elfrieda Wolff III","email":"tsmith@gmail.com","phone_number":"877-563-5814","address":"117 Crist Common\nSouth Judy, NC 02126-9328","job":"Food Preparation","company":"Grimes, Mraz and Schneider","card_type":"Visa","account_number":"3528458579511988"},{"_id":"848a994a-610b-44a9-abdd-4348efc8fe96","id":10,"full_name":"Arthur Strosin","email":"wlesch@hotmail.com","phone_number":"855-836-4544","address":"801 Moen Village\nPort Edgar, RI 55127-6065","job":"Septic Tank Servicer","company":"Murazik-Mohr","card_type":"MasterCard","account_number":"4929288250711"}],"articles":[{"_id":"3593dbd2-d1e4-4b22-8a76-0a29c00c86ad","id":1,"title":"Streamline compelling markets","description":"Laborum aut et autem. Eveniet sequi in eaque cum culpa atque ea voluptates. Natus provident asperiores quas odio.","views":60472,"like":9264,"dislike":3668,"date_published":"11-12-2015"},{"_id":"3721906a-94c4-4486-93ed-f72b631879bf","id":2,"title":"Transform efficient users","description":"Quia maiores tempore ut error qui qui ad. Eius illo culpa asperiores quam et. Ex hic est maxime quos nesciunt porro libero.","views":57306,"like":5185,"dislike":3128,"date_published":"21-03-1980"},{"_id":"85916629-caf7-4646-97f3-d6bb3dfcbb1a","id":3,"title":"Cultivate intuitive infomediaries","description":"Id ducimus temporibus vel aliquam id eveniet totam vel. Quod dolorem earum voluptatem ipsum. Deleniti neque est sunt magni maiores. Adipisci deserunt alias dolores dignissimos odio ipsa quasi.","views":86253,"like":521,"dislike":8555,"date_published":"30-06-2010"},{"_id":"d4958f7f-22f1-43c5-a325-9cf6def6b1d1","id":4,"title":"Innovate collaborative architectures","description":"Laudantium minus molestias aliquid et maiores. Amet aperiam nostrum dolorem praesentium. Delectus veritatis eum voluptas enim voluptas. Fuga qui qui est est doloremque voluptatem.","views":88856,"like":5824,"dislike":3399,"date_published":"25-11-2008"},{"_id":"b8afc58c-a495-469a-9af8-a49423bf8105","id":5,"title":"Facilitate virtual e-tailers","description":"Et ad laudantium quia necessitatibus. Nobis consectetur repudiandae neque voluptatem est. Quo distinctio consequatur velit. Cupiditate est laudantium magnam.","views":84904,"like":2930,"dislike":5040,"date_published":"03-09-1978"},{"_id":"4b60be50-db45-4da6-b8ab-6e90d9452877","id":6,"title":"Reintermediate cutting-edge bandwidth","description":"Cum quam repudiandae ut. Optio mollitia qui molestiae autem ipsum dolores. Omnis dignissimos natus tempore cupiditate aliquam ut consequatur.","views":45919,"like":7301,"dislike":396,"date_published":"27-12-1981"},{"_id":"ec401f2e-98cc-49d1-a5b4-d9573168fa3d","id":7,"title":"Transform B2B convergence","description":"Praesentium maxime quas veritatis nesciunt qui libero incidunt. Saepe voluptates est consequuntur. Delectus iure voluptatem sunt et similique dolores.","views":80646,"like":793,"dislike":5811,"date_published":"11-02-1990"},{"_id":"f85c2164-ebe4-4424-b2f8-c7fd4e93612f","id":8,"title":"Embrace back-end vortals","description":"Autem vero a fuga sint ut molestiae blanditiis aliquam. Et vitae enim sit repellendus cum necessitatibus voluptatem ipsam. Eaque pariatur repellat non ut totam aut neque.","views":78396,"like":9691,"dislike":4100,"date_published":"04-02-2007"},{"_id":"c927c2d7-4a61-4a52-98e3-0d1ed7794ee8","id":9,"title":"Embrace dynamic technologies","description":"Necessitatibus consequatur harum earum iste. Quia repellendus adipisci vero dolore. Maxime quia mollitia nobis modi. Non maiores numquam enim. Neque animi fugit optio ut repellat molestiae veritatis.","views":80737,"like":460,"dislike":4581,"date_published":"12-01-1977"},{"_id":"08a5d266-edcf-4c2c-aede-b8977877d604","id":10,"title":"Visualize scalable content","description":"Rerum atque voluptate reiciendis ut voluptas. Explicabo eos vitae non nemo pariatur. Nisi eveniet voluptate perspiciatis soluta libero et est mollitia. Laborum minus enim itaque nobis esse illum.","views":95422,"like":5572,"dislike":9045,"date_published":"09-02-1970"}]}